odoo/addons/l10n_it_fiscal_document_type/README.rst
odoo/addons/l10n_it_fiscal_document_type/__init__.py
odoo/addons/l10n_it_fiscal_document_type/__manifest__.py
odoo/addons/l10n_it_fiscal_document_type/data/fiscal.document.type.csv
odoo/addons/l10n_it_fiscal_document_type/i18n/am.po
odoo/addons/l10n_it_fiscal_document_type/i18n/ar.po
odoo/addons/l10n_it_fiscal_document_type/i18n/bg.po
odoo/addons/l10n_it_fiscal_document_type/i18n/bs.po
odoo/addons/l10n_it_fiscal_document_type/i18n/ca.po
odoo/addons/l10n_it_fiscal_document_type/i18n/cs.po
odoo/addons/l10n_it_fiscal_document_type/i18n/da.po
odoo/addons/l10n_it_fiscal_document_type/i18n/de.po
odoo/addons/l10n_it_fiscal_document_type/i18n/el_GR.po
odoo/addons/l10n_it_fiscal_document_type/i18n/en_GB.po
odoo/addons/l10n_it_fiscal_document_type/i18n/es.po
odoo/addons/l10n_it_fiscal_document_type/i18n/es_AR.po
odoo/addons/l10n_it_fiscal_document_type/i18n/es_CL.po
odoo/addons/l10n_it_fiscal_document_type/i18n/es_CO.po
odoo/addons/l10n_it_fiscal_document_type/i18n/es_CR.po
odoo/addons/l10n_it_fiscal_document_type/i18n/es_DO.po
odoo/addons/l10n_it_fiscal_document_type/i18n/es_EC.po
odoo/addons/l10n_it_fiscal_document_type/i18n/es_ES.po
odoo/addons/l10n_it_fiscal_document_type/i18n/es_MX.po
odoo/addons/l10n_it_fiscal_document_type/i18n/es_PE.po
odoo/addons/l10n_it_fiscal_document_type/i18n/es_PY.po
odoo/addons/l10n_it_fiscal_document_type/i18n/es_VE.po
odoo/addons/l10n_it_fiscal_document_type/i18n/et.po
odoo/addons/l10n_it_fiscal_document_type/i18n/eu.po
odoo/addons/l10n_it_fiscal_document_type/i18n/fa.po
odoo/addons/l10n_it_fiscal_document_type/i18n/fi.po
odoo/addons/l10n_it_fiscal_document_type/i18n/fr.po
odoo/addons/l10n_it_fiscal_document_type/i18n/fr_CA.po
odoo/addons/l10n_it_fiscal_document_type/i18n/fr_CH.po
odoo/addons/l10n_it_fiscal_document_type/i18n/gl.po
odoo/addons/l10n_it_fiscal_document_type/i18n/gl_ES.po
odoo/addons/l10n_it_fiscal_document_type/i18n/he.po
odoo/addons/l10n_it_fiscal_document_type/i18n/hr.po
odoo14_addon_l10n_it_fiscal_document_type-14.0.1.1.1.dist-info/METADATA
odoo14_addon_l10n_it_fiscal_document_type-14.0.1.1.1.dist-info/WHEEL
odoo14_addon_l10n_it_fiscal_document_type-14.0.1.1.1.dist-info/top_level.txt
odoo14_addon_l10n_it_fiscal_document_type-14.0.1.1.1.dist-info/RECORD
