Metadata-Version: 2.1
Name: odoo14-addon-l10n-it-fiscal-document-type
Version: 14.0.1.1.1
Summary: ITA - Tipi di documento fiscale per dichiarativi
Home-page: https://github.com/OCA/l10n-italy
Author: Link It srl, Odoo Community Association (OCA)
Author-email: support@odoo-community.org
License: AGPL-3
Platform: UNKNOWN
Classifier: Programming Language :: Python
Classifier: Framework :: Odoo
Classifier: Framework :: Odoo :: 14.0
Classifier: License :: OSI Approved :: GNU Affero General Public License v3
Requires-Python: >=3.6
Requires-Dist: odoo14-addon-l10n-it-account
Requires-Dist: odoo (<14.1dev,>=14.0a)
